{
  "id": "37",
  "name_pl": "Spięcie izometryczne w siadzie typu V (V Sit Hold)",
  "name_en": null,
  "muscle_group_id": "2",
  "muscle_group_name": "Brzuch",
  "photos": [
    "2758"
  ],
  "raw_data": {
    "bui": true,
    "comp": false,
    "desc_pl": "Spięcie izometryczne w siadzie typu V (V Sit Hold)",
    "gym": false,
    "home": true,
    "id": "37",
    "iso": false,
    "photo_1": "2758",
    "photo_2": "",
    "photo_3": "",
    "photo_4": "",
    "stat": true,
    "use": false
  }
}