{
  "id": "1713",
  "name_pl": "Przysiad z ramionami nad głową jednonóż do podwyższenia (Pistol Squat)",
  "name_en": null,
  "muscle_group_id": "9",
  "muscle_group_name": "Czworogłowe ud",
  "photos": [
    "5916",
    "5920"
  ],
  "raw_data": {
    "bui": true,
    "comp": true,
    "desc_pl": "Przysiad z ramionami nad głową jednonóż do podwyższenia (Pistol Squat)",
    "gym": false,
    "home": true,
    "id": "1713",
    "iso": false,
    "photo_1": "5916",
    "photo_2": "5920",
    "photo_3": "",
    "photo_4": "",
    "stat": false,
    "use": false
  }
}