{
  "id": "1079",
  "name_pl": "Odwodzenie zgiętej do prostej nogi do tyłu z gumą (długą) na kostce stojąc",
  "name_en": null,
  "muscle_group_id": "3",
  "muscle_group_name": "Pośladki",
  "photos": [
    "8852",
    "8853"
  ],
  "raw_data": {
    "bui": true,
    "comp": false,
    "desc_pl": "Odwodzenie zgiętej do prostej nogi do tyłu z gumą (długą) na kostce stojąc",
    "gym": false,
    "home": true,
    "id": "1079",
    "iso": true,
    "photo_1": "8852",
    "photo_2": "8853",
    "photo_3": "",
    "photo_4": "",
    "stat": false,
    "use": false
  }
}