{
  "id": "2127",
  "name_pl": "Wyciskanie JM sztangi leżąc (JM Press)",
  "name_en": null,
  "muscle_group_id": "11",
  "muscle_group_name": "Triceps",
  "photos": [
    "6290",
    "6291"
  ],
  "raw_data": {
    "bui": true,
    "comp": true,
    "desc_pl": "Wyciskanie JM sztangi leżąc (JM Press)",
    "gym": true,
    "home": false,
    "id": "2127",
    "iso": false,
    "photo_1": "6290",
    "photo_2": "6291",
    "photo_3": "",
    "photo_4": "",
    "stat": false,
    "use": false
  }
}